musical_notes/__init__.py
musical_notes/chords.py
musical_notes/cli.py
musical_notes/convert_degrees.py
musical_notes/half_step.py
musical_notes/harmonic_field.py
musical_notes/minors.py
musical_notes/scales.py
musical_notes/triads.py
musical_notes-0.1.0.dist-info/entry_points.txt
musical_notes-0.1.0.dist-info/LICENSE.md
musical_notes-0.1.0.dist-info/METADATA
musical_notes-0.1.0.dist-info/WHEEL
musical_notes-0.1.0.dist-info/RECORD
