Metadata-Version: 2.1
Name: musical-notes
Version: 0.1.0
Summary: Musical Notes CLI: A command-line tool for music students to practice identifying and memorizing musical notes.
License: MIT
Author: drigols
Author-email: drigols.creative@gmail.com
Requires-Python: >=3.11,<4.0
Classifier: Development Status :: 5 - Production/Stable
Classifier: Environment :: Console
Classifier: License :: OSI Approved :: MIT License
Classifier: Natural Language :: English
Classifier: Programming Language :: Python :: 3
Classifier: Programming Language :: Python :: 3.11
Classifier: Programming Language :: Python :: 3.11
Classifier: Topic :: Education
Requires-Dist: rich (>=13.3.4,<14.0.0)
Requires-Dist: typer (>=0.7.0,<0.8.0)
Project-URL: Documentation, https://musical-notes.readthedocs.io/en/latest/
Project-URL: Issue Tracker, https://github.com/drigols/musical-notes/issues
Project-URL: Repository, https://github.com/drigols/musical-notes
